hub_city/__init__.py
hub_city/app/NotoSansCJK-Bold.ttc
hub_city/app/_20250321_001_nssm.pyd
hub_city/app/_20250321_002_nssm.pyd
hub_city/app/__init__.py
hub_city/app/app.pyd
hub_city/app/dataset.pyd
hub_city/app/font.pyd
hub_city/app/image.pyd
hub_city/app/logger.pyd
hub_city/app/utils.pyd
hub_city/app/web.pyd
hub_city/data/__init__.py
hub_city/data/data.pyd
hub_city/log/__init__.py
hub_city/log/log.pyd
hub_city/model/__init__.py
hub_city/model/model.pyd
hub_city/utils/__init__.py
hub_city/utils/utils.pyd
hub_city-0.7.dist-info/METADATA
hub_city-0.7.dist-info/WHEEL
hub_city-0.7.dist-info/top_level.txt
hub_city-0.7.dist-info/RECORD
