Metadata-Version: 2.1
Name: hub_city
Version: 0.7
Summary: this is a program for EE
Author: 
Author-email: 
Requires-Dist: numpy ==1.23.5
Requires-Dist: onnx ==1.16.2
Requires-Dist: onnxruntime ==1.18.1
Requires-Dist: onnxruntime-gpu ==1.18.1
Requires-Dist: onnxscript ==0.1.0.dev20240905
Requires-Dist: opencv-contrib-python ==4.10.0.84
Requires-Dist: opencv-python ==4.10.0.84
Requires-Dist: Pillow ==9.5.0
Requires-Dist: matplotlib ==3.7.5
Requires-Dist: matplotlib-inline ==0.1.6
Requires-Dist: requests ==2.31.0
